{
  "hash": "f22a2113",
  "configHash": "633e5cc2",
  "lockfileHash": "a62cb383",
  "browserHash": "b80d5e6c",
  "optimized": {
    "react": {
      "src": "../../react/index.js",
      "file": "react.js",
      "fileHash": "4acfc2fd",
      "needsInterop": true
    },
    "react-dom": {
      "src": "../../react-dom/index.js",
      "file": "react-dom.js",
      "fileHash": "d1c4d458",
      "needsInterop": true
    },
    "react/jsx-dev-runtime": {
      "src": "../../react/jsx-dev-runtime.js",
      "file": "react_jsx-dev-runtime.js",
      "fileHash": "cddbe7c5",
      "needsInterop": true
    },
    "react/jsx-runtime": {
      "src": "../../react/jsx-runtime.js",
      "file": "react_jsx-runtime.js",
      "fileHash": "9962b6cf",
      "needsInterop": true
    },
    "lucide-react": {
      "src": "../../lucide-react/dist/esm/lucide-react.js",
      "file": "lucide-react.js",
      "fileHash": "a25458f0",
      "needsInterop": false
    },
    "react-dom/client": {
      "src": "../../react-dom/client.js",
      "file": "react-dom_client.js",
      "fileHash": "de35fc2b",
      "needsInterop": true
    },
    "react-responsive-masonry": {
      "src": "../../react-responsive-masonry/es/index.js",
      "file": "react-responsive-masonry.js",
      "fileHash": "5110b04f",
      "needsInterop": false
    },
    "react-router": {
      "src": "../../react-router/dist/development/index.mjs",
      "file": "react-router.js",
      "fileHash": "596b6fb4",
      "needsInterop": false
    },
    "recharts": {
      "src": "../../recharts/es6/index.js",
      "file": "recharts.js",
      "fileHash": "daa49c35",
      "needsInterop": false
    }
  },
  "chunks": {
    "chunk-SVG7M4VJ": {
      "file": "chunk-SVG7M4VJ.js"
    },
    "chunk-SNSCGMK6": {
      "file": "chunk-SNSCGMK6.js"
    },
    "chunk-2YIMICFJ": {
      "file": "chunk-2YIMICFJ.js"
    }
  }
}